{
    "title": "框架开发手册",
    "description": "框架开发手册",
    "author": "pengm",
    "generator": "site",
    "language": "zh-hans",
    "gitbook": "2.6.4",
    "links": {
        "sidebar": {
            "Home": "http://www.increator.cn"
        }
    },
    "plugins": [
        "favicon@^0.0.2" 
        "tbfed-pagefooter"
    ],
    "pluginsConfig": {
        "tbfed-pagefooter": {
            "copyright": "Copyright &copy increator.cn 2017 浙江创建科技有限公司",
            "modify_label": "该文件修订时间：",
            "modify_format": "YYYY-MM-DD HH:mm:ss"
        },
        "favicon": {
            "shortcut": "favicon.ico",
            "bookmark": "favicon.ico"
        }, 
        "anchor-navigation-ex": {
            "isRewritePageTitle": false,
            "tocLevel1Icon": "fa fa-hand-o-right",
            "tocLevel2Icon": "fa fa-hand-o-right",
            "tocLevel3Icon": "fa fa-hand-o-right"
        }
    }
}